programmable_pomodoro/.DS_Store
programmable_pomodoro/__init__.py
programmable_pomodoro/audio/alarm.wav
programmable_pomodoro-0.1.1.dist-info/LICENSE
programmable_pomodoro-0.1.1.dist-info/WHEEL
programmable_pomodoro-0.1.1.dist-info/METADATA
programmable_pomodoro-0.1.1.dist-info/RECORD
