Metadata-Version: 2.1
Name: programmable-pomodoro
Version: 0.1.1
Summary: A programmable pomodoro timer.
Author: Matthew Caseres
Author-email: matthewcaseres@outlook.com
Requires-Python: >=3.7,<4.0
Classifier: Programming Language :: Python :: 3
Classifier: Programming Language :: Python :: 3.7
Classifier: Programming Language :: Python :: 3.8
Classifier: Programming Language :: Python :: 3.9
Requires-Dist: aioconsole (>=0.3.2,<0.4.0)
Requires-Dist: colorama (>=0.4.4,<0.5.0)
